{"version":1,"resource":"file:///home/yunis/Development/code/phase-1/phase-1-javascript-variables-lab/index.js","entries":[{"id":"OxI4.js","timestamp":1669204017930},{"id":"6IDe.js","timestamp":1669204061633},{"id":"hq1m.js","timestamp":1669204075279},{"id":"aLjX.js","timestamp":1669204129724},{"id":"m3aK.js","timestamp":1669204627634},{"id":"iuhp.js","timestamp":1669204729128},{"id":"bPuU.js","timestamp":1669204851671},{"id":"1duj.js","timestamp":1669204966427},{"id":"GtyG.js","timestamp":1669205207455},{"id":"OyU1.js","timestamp":1669205287527},{"id":"c54B.js","timestamp":1669205347740},{"id":"XChJ.js","timestamp":1669205463619},{"id":"sdl4.js","timestamp":1669205543030},{"id":"cWZ1.js","timestamp":1669207195970}]}